easy_letters/__init__.py
easy_letters/connectors.py
easy_letters/similarity_search.py
easy_letters-0.1.9.dist-info/LICENSE
easy_letters-0.1.9.dist-info/METADATA
easy_letters-0.1.9.dist-info/WHEEL
easy_letters-0.1.9.dist-info/RECORD
