Metadata-Version: 2.3
Name: easy-letters
Version: 0.1.9
Summary: A Python library for generating draft application letters using generative AI
License: MIT
Author: Hassan Abedi
Author-email: hassan.abedi.t@gmail.com
Maintainer: Hassan Abedi
Maintainer-email: hassan.abedi.t@gmail.com
Requires-Python: >=3.10,<4.0
Classifier: License :: OSI Approved :: MIT License
Classifier: Programming Language :: Python :: 3
Classifier: Programming Language :: Python :: 3.10
Classifier: Programming Language :: Python :: 3.11
Classifier: Programming Language :: Python :: 3.12
Classifier: Programming Language :: Python :: 3.13
Requires-Dist: openai (>=1.16.1,<2.0.0)
Requires-Dist: qdrant-client (>=1.8.2,<2.0.0)
Project-URL: Repository, https://github.com/habedi/easy-letters
